bip39.py
bip39/__init__.py
bip39/bip39.py
bip39-0.0.1.data/scripts/bip39.py
bip39-0.0.1.dist-info/LICENSE
bip39-0.0.1.dist-info/METADATA
bip39-0.0.1.dist-info/WHEEL
bip39-0.0.1.dist-info/top_level.txt
bip39-0.0.1.dist-info/RECORD
